cybmitest/BMI.py
cybmitest-0.0.0.1.dist-info/METADATA
cybmitest-0.0.0.1.dist-info/WHEEL
cybmitest-0.0.0.1.dist-info/top_level.txt
cybmitest-0.0.0.1.dist-info/RECORD
